{
  "id": "91443",
  "title": "Topic: UFC 323UFC 323: Dvalishvili vs. Yan 2",
  "totalPages": 138,
  "posts": [
    {
      "id": "1566357",
      "author": "Tapology",
      "authorUrl": "/profiles/tapology",
      "timestamp": "2025-09-09T23:47:00-05:00",
      "content": "The official Tapology discussion thread for the event!",
      "upvotes": 45,
      "downvotes": 0
    },
    {
      "id": "1605968",
      "author": "evergreenrider",
      "authorUrl": "/profiles/evergreenrider",
      "timestamp": "2025-12-07T01:23:00-05:00",
      "content": "A shoulder dislocation that relocated on its own? He grabbed his elbow...",
      "upvotes": 0,
      "downvotes": 2
    },
    {
      "id": "1605969",
      "author": "Noxx",
      "authorUrl": "/profiles/noxx",
      "timestamp": "2025-12-07T01:23:00-05:00",
      "content": "Predictions: 9 of 14 Winners, 3 Perfect, 620 Points\n|\nTied for 1148th\n\nMegan Olivi mentioned that it was a shoulder dislocation and not an elbow dislocation. Regardless, I'm glad it was no break. That would've been a ****** recovery for Pantoja if that were the case",
      "upvotes": 1,
      "downvotes": 0
    },
    {
      "id": "1605970",
      "author": "evergreenrider",
      "authorUrl": "/profiles/evergreenrider",
      "timestamp": "2025-12-07T01:24:00-05:00",
      "content": "Pantoja with a page out of the dillasnake book",
      "upvotes": 0,
      "downvotes": 2
    },
    {
      "id": "1605971",
      "author": "NNNNNNN",
      "authorUrl": "/profiles/nnnnnnn",
      "timestamp": "2025-12-07T01:25:00-05:00",
      "content": "Predictions: 8 of 14 Winners, 3 Perfect, 540 Points\n|\nTied for 3028th\n\nwhere are the merab glazers/simps, the 91% of you?\ni want to read salt and rage\nmaybe tomorrow? <3",
      "upvotes": 1,
      "downvotes": 4
    },
    {
      "id": "1605972",
      "author": "madaMMA",
      "authorUrl": "/profiles/madamma",
      "timestamp": "2025-12-07T01:25:00-05:00",
      "content": "Predictions: 8 of 14 Winners, 2 Perfect, 490 Points\n|\nTied for 4399th\n\nYan is a top 15 fighter oat now (if you count the O’Malley robbery)",
      "upvotes": 1,
      "downvotes": 2
    },
    {
      "id": "1605973",
      "author": "Blackbet25",
      "authorUrl": "/profiles/blackbet25",
      "timestamp": "2025-12-07T01:26:00-05:00",
      "content": "Predictions: 12 of 14 Winners, 6 Perfect, 830 Points\n|\n12th Place",
      "upvotes": 9,
      "downvotes": 2
    },
    {
      "id": "1605975",
      "author": "NNNNNNN",
      "authorUrl": "/profiles/nnnnnnn",
      "timestamp": "2025-12-07T01:27:00-05:00",
      "content": "Predictions: 8 of 14 Winners, 3 Perfect, 540 Points\n|\nTied for 3028th\n\n@Blackbet25 incredible, bro",
      "upvotes": 0,
      "downvotes": 0
    },
    {
      "id": "1605976",
      "author": "D1D4K10",
      "authorUrl": "/profiles/d1d4k10",
      "timestamp": "2025-12-07T01:30:00-05:00",
      "content": "Predictions: 6 of 14 Winners, 3 Perfect, 415 Points\n|\nTied for 6329th\n\nCrazy card, can’t remember when I was this low",
      "upvotes": 0,
      "downvotes": 0
    },
    {
      "id": "1605977",
      "author": "Noxx",
      "authorUrl": "/profiles/noxx",
      "timestamp": "2025-12-07T01:32:00-05:00",
      "content": "Predictions: 9 of 14 Winners, 3 Perfect, 620 Points\n|\nTied for 1148th\n\nThis card spawned great future contenders. Both Talbott and Taira winning against a previous champs. And Van now holding the flyweight belt is actually a good thing looking forward. I hope Pantoja can fully recover and can rematch Van at some point. Even though it seems like the UFC wants Taira to get the title shot next.",
      "upvotes": 0,
      "downvotes": 0
    },
    {
      "id": "1605978",
      "author": "The Giraffe",
      "authorUrl": "/profiles/the%20giraffe",
      "timestamp": "2025-12-07T01:33:00-05:00",
      "content": "Predictions: 10 of 14 Winners, 2 Perfect, 595 Points\n|\nTied for 1580th\n\nFor anyone who is curious\n\nMonthly reminder that Joe Rogan (and to a lesser extent DC) don't know how to score fights.",
      "upvotes": 0,
      "downvotes": 2
    },
    {
      "id": "1605979",
      "author": "Noxx",
      "authorUrl": "/profiles/noxx",
      "timestamp": "2025-12-07T01:36:00-05:00",
      "content": "Predictions: 9 of 14 Winners, 3 Perfect, 620 Points\n|\nTied for 1148th\n\nTime to rewatch Iwo vs Ibo before I go to sleep",
      "upvotes": 0,
      "downvotes": 0
    },
    {
      "id": "1605980",
      "author": "AyyLmaonnaise",
      "authorUrl": "/profiles/ayylmaonnaise",
      "timestamp": "2025-12-07T01:36:00-05:00",
      "content": "Predictions: 9 of 14 Winners, 2 Perfect, 595 Points\n|\nTied for 1603rd\n\nbest card of the year",
      "upvotes": 4,
      "downvotes": 1
    },
    {
      "id": "1605981",
      "author": "connorbrown16",
      "authorUrl": "/profiles/connorbrown16",
      "timestamp": "2025-12-07T01:37:00-05:00",
      "content": "Predictions: 7 of 14 Winners, 3 Perfect, 495 Points\n|\nTied for 4327th\n\n@AyyLmaonnaise you picked the right one to go to lol",
      "upvotes": 2,
      "downvotes": 0
    },
    {
      "id": "1605982",
      "author": "Parlay Boss",
      "authorUrl": "/profiles/parlay%20boss",
      "timestamp": "2025-12-07T01:38:00-05:00",
      "content": "Predictions: 11 of 14 Winners, 2 Perfect, 655 Points\n|\nTied for 666th\n\nSo happy for Yan! He finally got his revenge 👊",
      "upvotes": 2,
      "downvotes": 0
    },
    {
      "id": "1605983",
      "author": "madaMMA",
      "authorUrl": "/profiles/madamma",
      "timestamp": "2025-12-07T01:40:00-05:00",
      "content": "Predictions: 8 of 14 Winners, 2 Perfect, 490 Points\n|\nTied for 4399th\n\n@The Giraffe Moreno clearly won r1",
      "upvotes": 3,
      "downvotes": 0
    },
    {
      "id": "1605984",
      "author": "Littledohyo",
      "authorUrl": "/profiles/littledohyo",
      "timestamp": "2025-12-07T01:42:00-05:00",
      "content": "Predictions: 11 of 14 Winners, 4 Perfect, 735 Points\n|\nTied for 154th\n\nI am happy with the card but I think back to the start of Van Pantoja and it was starting so hot, I'm so bummed it ended early, even without the obviously sadness an injury causes. You just don't see people disrespect vaunted strikers like that very often.",
      "upvotes": 2,
      "downvotes": 0
    },
    {
      "id": "1605985",
      "author": "Anonymous",
      "authorUrl": "",
      "timestamp": "2025-12-07T01:42:00-05:00",
      "content": "Predictions: 7 of 14 Winners, 3 Perfect, 505 Points\n|\nTied for 4104th\n\nmain event was ******* amazing but how was this card of the year? horrible ending to the co main, moreno early stoppage, and jan got robbed",
      "upvotes": 1,
      "downvotes": 3
    },
    {
      "id": "1605987",
      "author": "AyyLmaonnaise",
      "authorUrl": "/profiles/ayylmaonnaise",
      "timestamp": "2025-12-07T01:42:00-05:00",
      "content": "Predictions: 9 of 14 Winners, 2 Perfect, 595 Points\n|\nTied for 1603rd\n\n@connorbrown16 yessir I knew there was no way the card could be bad with this lineup",
      "upvotes": 1,
      "downvotes": 0
    },
    {
      "id": "1605991",
      "author": "The Giraffe",
      "authorUrl": "/profiles/the%20giraffe",
      "timestamp": "2025-12-07T01:44:00-05:00",
      "content": "Predictions: 10 of 14 Winners, 2 Perfect, 595 Points\n|\nTied for 1580th\n\n@madaMMA\n\nYou don't know how to score MMA fights under the Unified Ruleset either.  Congrats, you could be a UFC commentator like Joe Rogan.",
      "upvotes": 1,
      "downvotes": 0
    },
    {
      "id": "1605993",
      "author": "TapeIsBestMMABase",
      "authorUrl": "/profiles/tapeisbestmmabase",
      "timestamp": "2025-12-07T01:47:00-05:00",
      "content": "Predictions: 7 of 14 Winners, 5 Perfect, 540 Points\n|\nTied for 3137th\n\n@corbin Nah it definitely was a legit draw.",
      "upvotes": 2,
      "downvotes": 0
    },
    {
      "id": "1566357",
      "author": "Tapology",
      "authorUrl": "/profiles/tapology",
      "timestamp": "2025-09-09T23:47:00-05:00",
      "content": "The official Tapology discussion thread for the event!",
      "upvotes": 45,
      "downvotes": 0
    },
    {
      "id": "1605996",
      "author": "madaMMA",
      "authorUrl": "/profiles/madamma",
      "timestamp": "2025-12-07T01:49:00-05:00",
      "content": "Predictions: 8 of 14 Winners, 2 Perfect, 490 Points\n|\nTied for 4399th\n\n@The Giraffe how? zero significant strikes landed on the feet and Moreno had the most significant moment of the round with a close submission attempt which is scored as effective grappling. Taira didn’t do anything to win that round zero effective striking and zero effective grappling",
      "upvotes": 2,
      "downvotes": 2
    },
    {
      "id": "1605997",
      "author": "kovu",
      "authorUrl": "/profiles/kovu",
      "timestamp": "2025-12-07T01:51:00-05:00",
      "content": "Predictions: 8 of 14 Winners, 2 Perfect, 545 Points\n|\nTied for 2865th\n\nWelp im gonna grab a box of tissues and rewatch Ibo vs Iwo 5x over",
      "upvotes": 2,
      "downvotes": 1
    },
    {
      "id": "1605999",
      "author": "el222",
      "authorUrl": "/profiles/el222",
      "timestamp": "2025-12-07T01:52:00-05:00",
      "content": "Predictions: 1 of 3 Winners, 0 Perfect, 50 Points\n|\nTied for 8994th\n\nmy goat got his belt back 🐐❤️ LETS GO PETR",
      "upvotes": 2,
      "downvotes": 1
    },
    {
      "id": "1606000",
      "author": "kovu",
      "authorUrl": "/profiles/kovu",
      "timestamp": "2025-12-07T01:58:00-05:00",
      "content": "Predictions: 8 of 14 Winners, 2 Perfect, 545 Points\n|\nTied for 2865th\n\nMERAB GOT A BONUS FOR THAT PERFORMANCE OVER ASLAN AND DUNCAN......are you fking kidding me??????",
      "upvotes": 3,
      "downvotes": 2
    },
    {
      "id": "1606001",
      "author": "elitemmapicks",
      "authorUrl": "/profiles/elitemmapicks",
      "timestamp": "2025-12-07T02:00:00-05:00",
      "content": "Predictions: 8 of 14 Winners, 3 Perfect, 530 Points\n|\nTied for 3281st",
      "upvotes": 0,
      "downvotes": 0
    },
    {
      "id": "1606003",
      "author": "The Giraffe",
      "authorUrl": "/profiles/the%20giraffe",
      "timestamp": "2025-12-07T02:08:00-05:00",
      "content": "Predictions: 10 of 14 Winners, 2 Perfect, 595 Points\n|\nTied for 1580th\n\n@madaMMA\n\nA submission attempt is indeed scored as effective grappling.  But it proved to be a rather weak and insignificant attempt and he stayed on his back for 3 or so minutes not transitiong to a more advantageous position, and not locking up to a more substantive submission attempt.  He was just stuck doing nothing, holding on to an attempt that had already failed.  Taira demonstrated that he was perfectly fine, and those little rabbit punches he landed + transitioning to a front headlock at the end with those little knees was enough.  Taira in effect had his own effective grappling that scored, while also landing strikes.\n\nIt's not like it was a 4 minute sub attempt.  It was a sub attempt that failed in short order, and then he was stuck in that position, doing nothing, not transitioning, not locking in a stronger attempt.  That's the reason that Mark Smith (not everyone's favorite ref tonight) warned that he was going to break it up.  He was right to do that.",
      "upvotes": 1,
      "downvotes": 1
    },
    {
      "id": "1606006",
      "author": "The Duck",
      "authorUrl": "/profiles/the%20duck",
      "timestamp": "2025-12-07T02:12:00-05:00",
      "content": "Predictions: 9 of 14 Winners, 4 Perfect, 630 Points\n|\nTied for 996th\n\nAnd honestly at least the co-main didn’t waste my time, it was a **** ending but it was only a minute so it was more disappointing, way better then 25 minute of ****\n\nOnly really bad thing about the card\n\n* Edited at 12.07.2025,  2:22 AM ET *",
      "upvotes": 0,
      "downvotes": 3
    },
    {
      "id": "1606009",
      "author": "Pflynn8",
      "authorUrl": "/profiles/pflynn8",
      "timestamp": "2025-12-07T02:19:00-05:00",
      "content": "Predictions: 7 of 14 Winners, 1 Perfect, 405 Points\n|\nTied for 6415th\n\nGreat card still gutted for Pantoja just a horrible way for his steak to end. Feels like we haven’t had an injury like that in forever.",
      "upvotes": 2,
      "downvotes": 0
    },
    {
      "id": "1606012",
      "author": "JackMercer",
      "authorUrl": "/profiles/jackmercer",
      "timestamp": "2025-12-07T02:40:00-05:00",
      "content": "Predictions: 10 of 14 Winners, 6 Perfect, 750 Points\n|\nTied for 115th\n\n**** this gay ass earth",
      "upvotes": 6,
      "downvotes": 2
    },
    {
      "id": "1606013",
      "author": "VidarBets",
      "authorUrl": "/profiles/vidarbets",
      "timestamp": "2025-12-07T02:51:00-05:00",
      "content": "Predictions: 0 of 0 Winners, 0 Perfect, 0 Points\n|\nTied for 9112th\n\nImagine being a Merab fan. Dude just loves to hug against the cage and lay on you. Glad Yan won.",
      "upvotes": 3,
      "downvotes": 0
    },
    {
      "id": "1606014",
      "author": "MMAutist",
      "authorUrl": "/profiles/mmautist",
      "timestamp": "2025-12-07T02:54:00-05:00",
      "content": "Predictions: 8 of 14 Winners, 4 Perfect, 565 Points\n|\nTied for 2358th\n\nLearned a valuable lesson tonight. Keep your mouth shut because anything can happen on any given night. Can't believe that I said Yan didn't have a chance.\n\n* Edited at 12.07.2025,  4:20 AM ET *",
      "upvotes": 0,
      "downvotes": 3
    },
    {
      "id": "1606019",
      "author": "ettu",
      "authorUrl": "/profiles/ettu",
      "timestamp": "2025-12-07T04:44:00-05:00",
      "content": "Predictions: 12 of 14 Winners, 7 Perfect, 905 Points\n|\nTied for 1st with 1 other",
      "upvotes": 4,
      "downvotes": 0
    },
    {
      "id": "1606020",
      "author": "mezzor",
      "authorUrl": "/profiles/mezzor",
      "timestamp": "2025-12-07T04:58:00-05:00",
      "content": "Predictions: 7 of 14 Winners, 5 Perfect, 565 Points\n|\nTied for 2439th\n\nVan fake win Yan fake win.\nEra of fake champs",
      "upvotes": 2,
      "downvotes": 2
    },
    {
      "id": "1606021",
      "author": "Kkkomboo",
      "authorUrl": "/profiles/kkkomboo",
      "timestamp": "2025-12-07T05:19:00-05:00",
      "content": "Predictions: 0 of 7 Winners, 0 Perfect, 0 Points\n|\nTied for 9112th",
      "upvotes": 1,
      "downvotes": 1
    },
    {
      "id": "1606025",
      "author": "Counter075wp",
      "authorUrl": "/profiles/counter075wp",
      "timestamp": "2025-12-07T06:27:00-05:00",
      "content": "Predictions: 8 of 14 Winners, 1 Perfect, 485 Points\n|\nTied for 4547th\n\nIt is sure that Merab will have a chance to regain his title on the other hand he would have to put more finish when he has taken it back",
      "upvotes": 0,
      "downvotes": 0
    },
    {
      "id": "1606026",
      "author": "rust",
      "authorUrl": "/profiles/rust",
      "timestamp": "2025-12-07T06:29:00-05:00",
      "content": "Predictions: 7 of 14 Winners, 3 Perfect, 470 Points\n|\nTied for 4972nd\n\ndont talk to me for a week",
      "upvotes": 4,
      "downvotes": 0
    },
    {
      "id": "1606027",
      "author": "Counter075wp",
      "authorUrl": "/profiles/counter075wp",
      "timestamp": "2025-12-07T06:47:00-05:00",
      "content": "Predictions: 8 of 14 Winners, 1 Perfect, 485 Points\n|\nTied for 4547th\n\n🤣",
      "upvotes": 0,
      "downvotes": 0
    },
    {
      "id": "1606028",
      "author": "Counter075wp",
      "authorUrl": "/profiles/counter075wp",
      "timestamp": "2025-12-07T06:50:00-05:00",
      "content": "Predictions: 8 of 14 Winners, 1 Perfect, 485 Points\n|\nTied for 4547th\n\n@rust me too 🤣",
      "upvotes": 1,
      "downvotes": 0
    },
    {
      "id": "1606029",
      "author": "Anonymous",
      "authorUrl": "",
      "timestamp": "2025-12-07T07:28:00-05:00",
      "content": "Predictions: 8 of 14 Winners, 4 Perfect, 580 Points\n|\nTied for 2008th\n\nFell asleep last night after Moreno vs Taira (I had a long day). Wake up to see Yan upset and Pantoja gets injured.",
      "upvotes": 0,
      "downvotes": 0
    },
    {
      "id": "1606033",
      "author": "battousai",
      "authorUrl": "/profiles/battousai",
      "timestamp": "2025-12-07T09:10:00-05:00",
      "content": "Predictions: 9 of 14 Winners, 2 Perfect, 570 Points\n|\nTied for 2170th\n\nWas watching this last night with a friend who doesnt follow MMA. His exact words when Iwo was looking tired, labored, and backing up towards the cage...very confidently, might I add....\n\n\"The Polish guy is so screwed\"\n\n**Iwo throws nuke**\n\nThe look on my friends face was priceless and pretty much made my entire evening. It was so obvious he had never seen anything like that before and it was awesome.",
      "upvotes": 1,
      "downvotes": 0
    },
    {
      "id": "1566357",
      "author": "Tapology",
      "authorUrl": "/profiles/tapology",
      "timestamp": "2025-09-09T23:47:00-05:00",
      "content": "The official Tapology discussion thread for the event!",
      "upvotes": 45,
      "downvotes": 0
    },
    {
      "id": "1606034",
      "author": "Richldnrd",
      "authorUrl": "/profiles/richldnrd",
      "timestamp": "2025-12-07T09:15:00-05:00",
      "content": "Predictions: 7 of 14 Winners, 3 Perfect, 455 Points\n|\nTied for 5342nd\n\nWas the fix in for Van?\nI'm just wondering how many thought this HUGE favorite losing by such an odd circumstance have the smell of rigged on the match? Theoreticall Pantoja could have done a job in the middle WWE style for Van while having a huge bet against himself. This would have given him the most paid per hour worker on the planet. Just a thought.",
      "upvotes": 0,
      "downvotes": 25
    },
    {
      "id": "1606040",
      "author": "flying_frontkick",
      "authorUrl": "/profiles/flying_frontkick",
      "timestamp": "2025-12-07T10:28:00-05:00",
      "content": "Predictions: 0 of 0 Winners, 0 Perfect, 0 Points\n|\nTied for 9112th\n\nGot a little bit of footage on the Moreno loss, he wasn't really going anywhere and Taira was landing hard punches. I feel like you gotta give Moreno more of a chance, but it wasn't looking good for him.\n\nPetr Yan surprised the hell out of me, I didn't see that coming and I swear if they try to book or hype up O'Malley because his robbery win over Yan, that will be ridiculous.\n\nMight be time to retire for Barboza, but the guy loves to fight. I think if he was going to retire he would have, but it's gotta be something to think about.",
      "upvotes": 3,
      "downvotes": 0
    },
    {
      "id": "1606074",
      "author": "Noxx",
      "authorUrl": "/profiles/noxx",
      "timestamp": "2025-12-07T14:19:00-05:00",
      "content": "Predictions: 9 of 14 Winners, 3 Perfect, 620 Points\n|\nTied for 1148th\n\nThe one time I finally pick Merab, he loses. So uhm... I will let you guys know my pick next time when Merab fights\n\n* Edited at 12.07.2025,  2:22 PM ET *",
      "upvotes": 15,
      "downvotes": 2
    },
    {
      "id": "1606095",
      "author": "Socalryno89",
      "authorUrl": "/profiles/socalryno89",
      "timestamp": "2025-12-07T16:38:00-05:00",
      "content": "Predictions: 8 of 14 Winners, 2 Perfect, 520 Points\n|\nTied for 3585th\n\nFor Blachowicz either Oezdemir, Rountree,Jiri, Azamat, Walker, Hill or even Zhang",
      "upvotes": 0,
      "downvotes": 2
    },
    {
      "id": "1606106",
      "author": "qqqqqq",
      "authorUrl": "/profiles/qqqqqq",
      "timestamp": "2025-12-07T17:19:00-05:00",
      "content": "Predictions: 8 of 14 Winners, 4 Perfect, 555 Points\n|\nTied for 2587th\n\n@Socalryno89 Please.\n\nJan blackavicz will never be close to the same echelon as MINYANG.\n\nWE would do unspeakable things to polish boy in that cage…",
      "upvotes": 0,
      "downvotes": 4
    },
    {
      "id": "1606140",
      "author": "KHAMZAT_MAKHACHEV",
      "authorUrl": "/profiles/khamzat_makhachev",
      "timestamp": "2025-12-07T22:38:00-05:00",
      "content": "Pantoja quit from the first sign of adversity.\n\nDoes a real champion wave off your opponent and beg for mercy, or does a champion get up no matter the injury?\n\nI don't care what happens to your arm, get up and fight.\n\nCoward.",
      "upvotes": 3,
      "downvotes": 14
    },
    {
      "id": "1606187",
      "author": "FireFist45",
      "authorUrl": "/profiles/firefist45",
      "timestamp": "2025-12-08T10:57:00-05:00",
      "content": "Predictions: 6 of 14 Winners, 1 Perfect, 365 Points\n|\nTied for 7187th\n\n@Noxx - I picked Merab too because I thought he would do just his old game plan.... the issue was two things - one Merab had to cut weight 4-5 times for 4 fights in one year. That takes a toll on your body.... he might be a machine but age will get to every man eventually and cutting weight.\nTwo... Petr Yan came prepared because he already fought Merab and knew his game plan and what it felt like to be in the cage with him. So he trained hard to defend Takedowns in certain positions. Thats super effective... just think if JDM  trained specifically how Islam do takedowns and get sprawl or knock him off balance. There will not be any Domination by Islam machakchev.",
      "upvotes": 0,
      "downvotes": 3
    },
    {
      "id": "1606188",
      "author": "FireFist45",
      "authorUrl": "/profiles/firefist45",
      "timestamp": "2025-12-08T10:58:00-05:00",
      "content": "Predictions: 6 of 14 Winners, 1 Perfect, 365 Points\n|\nTied for 7187th\n\n@Richldnrd  thats far fetched... unless there was a Vegas prop bet that said Pantoja will lose in Rd one from an injury;",
      "upvotes": 0,
      "downvotes": 0
    },
    {
      "id": "1606218",
      "author": "FireFist45",
      "authorUrl": "/profiles/firefist45",
      "timestamp": "2025-12-08T13:36:00-05:00",
      "content": "Predictions: 6 of 14 Winners, 1 Perfect, 365 Points\n|\nTied for 7187th\n\n@el222 - you know Sean O'Malley was licking his lips when Petr Yan won the belt right??",
      "upvotes": 2,
      "downvotes": 1
    },
    {
      "id": "1606225",
      "author": "Pflynn8",
      "authorUrl": "/profiles/pflynn8",
      "timestamp": "2025-12-08T14:25:00-05:00",
      "content": "Predictions: 7 of 14 Winners, 1 Perfect, 405 Points\n|\nTied for 6415th\n\nWhy did Dana feel the need to keep saying Pantoja had only dislocated his shoulder like they didn’t show 20 different angles of his elbow snapping",
      "upvotes": 4,
      "downvotes": 1
    },
    {
      "id": "1606343",
      "author": "MrBeanBean",
      "authorUrl": "/profiles/mrbeanbean",
      "timestamp": "2025-12-09T11:10:00-05:00",
      "content": "Predictions: 7 of 14 Winners, 4 Perfect, 525 Points\n|\nTied for 3556th\n\n@AyyLmaonnaise Im late to the party by a couple days, but just here to say that its really funny the way that ferreira ended up beating Vettori. Basically it was the exact way everyone was saying he wouldnt win the fight. Lets all agree now that Vettori is washed and just not good. For a fighter that is known mainly as a striker he is about as boring as they come and i would be glad to see him cut or used one more time to showcase someone who is way better than Bruno.\n\n* Edited at 12.09.2025, 11:10 AM ET *",
      "upvotes": 1,
      "downvotes": 0
    },
    {
      "id": "1606354",
      "author": "AyyLmaonnaise",
      "authorUrl": "/profiles/ayylmaonnaise",
      "timestamp": "2025-12-09T11:55:00-05:00",
      "content": "Predictions: 9 of 14 Winners, 2 Perfect, 595 Points\n|\nTied for 1603rd\n\nYeah lol Vettori is trash. I thought he had enough left to beat him but that round 3 showed he doesn’t have it in him. I still thought Brunno looked bad though, I don’t see him winning many fights in the rankings at all",
      "upvotes": 2,
      "downvotes": 3
    },
    {
      "id": "1606404",
      "author": "MrBeanBean",
      "authorUrl": "/profiles/mrbeanbean",
      "timestamp": "2025-12-09T16:55:00-05:00",
      "content": "Predictions: 7 of 14 Winners, 4 Perfect, 525 Points\n|\nTied for 3556th\n\n@AyyLmaonnaise I think we can fade brunno against a real top 15 guy, which i dont really see why ferreira shouldnt get a shot against someone inside the top 15 at this point. I think he will make a good bounce back opponent for someone like MVP or Dolidze",
      "upvotes": 2,
      "downvotes": 1
    },
    {
      "id": "1606411",
      "author": "AyyLmaonnaise",
      "authorUrl": "/profiles/ayylmaonnaise",
      "timestamp": "2025-12-09T17:18:00-05:00",
      "content": "Predictions: 9 of 14 Winners, 2 Perfect, 595 Points\n|\nTied for 1603rd\n\nI hope they use him as a stepping stone for someone like Ateba or CLD. He doesn’t deserve to hog a spot in the top 15",
      "upvotes": 0,
      "downvotes": 1
    },
    {
      "id": "1606425",
      "author": "Adrian99",
      "authorUrl": "/profiles/adrian99",
      "timestamp": "2025-12-09T19:03:00-05:00",
      "content": "Predictions: 9 of 14 Winners, 5 Perfect, 655 Points\n|\nTied for 713th\n\nMy night started out strong, had a rough main card, but in Petr we trust. I never lost faith and the division has been saved!",
      "upvotes": 1,
      "downvotes": 2
    },
    {
      "id": "1606426",
      "author": "The Duck",
      "authorUrl": "/profiles/the%20duck",
      "timestamp": "2025-12-09T19:04:00-05:00",
      "content": "Predictions: 9 of 14 Winners, 4 Perfect, 630 Points\n|\nTied for 996th\n\nWatching Vettori and Ortega recent fights shows why you need to defend and not eat flush headshots, Both guys are having  shorter career because eating punches clean ages you faster then having defense\n\nVettori is 32 years old and done",
      "upvotes": 0,
      "downvotes": 1
    },
    {
      "id": "1606602",
      "author": "MrBeanBean",
      "authorUrl": "/profiles/mrbeanbean",
      "timestamp": "2025-12-10T18:28:00-05:00",
      "content": "Predictions: 7 of 14 Winners, 4 Perfect, 525 Points\n|\nTied for 3556th\n\n@AyyLmaonnaise I would love it if the UFC somehow books Vettori's next fight vs Ateba, as long as ateba looks good in his next can crusher fight. Also I just think Brunno is a fun fighter and if robocop is in the top 15 then Brunno should be right on the cusp at the very least although we cant forget he missed weight... Lets see if CDL or Brunno deserve a top 15 fight, book it for spring 2026, great main event filler fight right there.",
      "upvotes": 1,
      "downvotes": 2
    },
    {
      "id": "1606720",
      "author": "qqqqqq",
      "authorUrl": "/profiles/qqqqqq",
      "timestamp": "2025-12-11T15:16:00-05:00",
      "content": "Predictions: 8 of 14 Winners, 4 Perfect, 555 Points\n|\nTied for 2587th\n\n@MrBeanBean Great fight to make.\n\nPrediction?\n\nGAUTIER 1st round murder.",
      "upvotes": 4,
      "downvotes": 0
    },
    {
      "id": "1642503",
      "author": "CheeseInTheClinch",
      "authorUrl": "/profiles/cheeseintheclinch",
      "timestamp": "2026-03-28T01:14:00-05:00",
      "content": "Predictions: 5 of 14 Winners, 2 Perfect, 355 Points\n|\nTied for 7366th\n\n.\n\n* Edited at 03.28.2026,  1:16 AM ET *",
      "upvotes": 0,
      "downvotes": 0
    },
    {
      "id": "1642504",
      "author": "CheeseInTheClinch",
      "authorUrl": "/profiles/cheeseintheclinch",
      "timestamp": "2026-03-28T01:16:00-05:00",
      "content": "Predictions: 5 of 14 Winners, 2 Perfect, 355 Points\n|\nTied for 7366th\n\n.\n\n* Edited at 03.28.2026,  1:16 AM ET *",
      "upvotes": 0,
      "downvotes": 0
    }
  ],
  "scrapedAt": "2026-03-28T10:31:20.867522+00:00"
}